skill_ovos_ddg/LICENSE
skill_ovos_ddg/MANIFEST.in
skill_ovos_ddg/README.md
skill_ovos_ddg/__init__.py
skill_ovos_ddg/version.py
skill_ovos_ddg/gui/all/ddg.png
skill_ovos_ddg/gui/all/logo.png
skill_ovos_ddg/gui/qt5/DuckDelegate.qml
skill_ovos_ddg/locale/ca-es/MiscBlacklist.voc
skill_ovos_ddg/locale/ca-es/More.voc
skill_ovos_ddg/locale/ca-es/Weather.voc
skill_ovos_ddg/locale/ca-es/age_at_death.intent
skill_ovos_ddg/locale/ca-es/alma_mater.intent
skill_ovos_ddg/locale/ca-es/birthdate.intent
skill_ovos_ddg/locale/ca-es/born.intent
skill_ovos_ddg/locale/ca-es/children.intent
skill_ovos_ddg/locale/ca-es/died.intent
skill_ovos_ddg/locale/ca-es/education.intent
skill_ovos_ddg/locale/ca-es/fields.intent
skill_ovos_ddg/locale/ca-es/known_for.intent
skill_ovos_ddg/locale/ca-es/no_answer.dialog
skill_ovos_ddg/locale/ca-es/official_website.intent
skill_ovos_ddg/locale/ca-es/resting_place.intent
skill_ovos_ddg/locale/ca-es/search_duck.intent
skill_ovos_ddg/locale/ca-es/skill.json
skill_ovos_ddg/locale/ca-es/thats all.dialog
skill_ovos_ddg/locale/ca-es/thesis.intent
skill_ovos_ddg/locale/ca-es/who.intent
skill_ovos_ddg/locale/da-dk/More.voc
skill_ovos_ddg/locale/da-dk/age_at_death.intent
skill_ovos_ddg/locale/da-dk/alma_mater.intent
skill_ovos_ddg/locale/da-dk/birthdate.intent
skill_ovos_ddg/locale/da-dk/born.intent
skill_ovos_ddg/locale/da-dk/children.intent
skill_ovos_ddg/locale/da-dk/died.intent
skill_ovos_ddg/locale/da-dk/education.intent
skill_ovos_ddg/locale/da-dk/fields.intent
skill_ovos_ddg/locale/da-dk/known_for.intent
skill_ovos_ddg/locale/da-dk/no_answer.dialog
skill_ovos_ddg/locale/da-dk/official_website.intent
skill_ovos_ddg/locale/da-dk/resting_place.intent
skill_ovos_ddg/locale/da-dk/search_duck.intent
skill_ovos_ddg/locale/da-dk/skill.json
skill_ovos_ddg/locale/da-dk/thats all.dialog
skill_ovos_ddg/locale/da-dk/thesis.intent
skill_ovos_ddg/locale/da-dk/who.intent
skill_ovos_ddg/locale/de-de/More.voc
skill_ovos_ddg/locale/de-de/age_at_death.intent
skill_ovos_ddg/skill_ddg.egg-info/PKG-INFO
skill_ovos_ddg/skill_ddg.egg-info/SOURCES.txt
skill_ovos_ddg/skill_ddg.egg-info/dependency_links.txt
skill_ovos_ddg/skill_ddg.egg-info/entry_points.txt
skill_ovos_ddg/skill_ddg.egg-info/requires.txt
skill_ovos_ddg/skill_ddg.egg-info/top_level.txt
skill_ddg-0.3.0.dist-info/LICENSE
skill_ddg-0.3.0.dist-info/METADATA
skill_ddg-0.3.0.dist-info/WHEEL
skill_ddg-0.3.0.dist-info/entry_points.txt
skill_ddg-0.3.0.dist-info/top_level.txt
skill_ddg-0.3.0.dist-info/RECORD
