Metadata-Version: 2.1
Name: skill-ddg
Version: 0.3.0
Summary: ovos duck duck go skill plugin
Home-page: https://github.com/OpenVoiceOS/skill-ovos-ddg
Author: JarbasAi
Author-email: jarbasai@mailfence.com
License: Apache-2.0
Keywords: ovos skill plugin
License-File: LICENSE
Requires-Dist: requests
Requires-Dist: langcodes
Requires-Dist: ovos-utils<1.0.0,>=0.0.35
Requires-Dist: ovos-workshop<4.0.0,>=3.4.0a1
Requires-Dist: ovos-translate-server-plugin
Requires-Dist: ovos-config<2.0.0,>=0.0.11
Requires-Dist: ovos-plugin-manager<1.0.0,>=0.0.26
Requires-Dist: ovos-date-parser
Requires-Dist: crf-query-xtract<1.0.0,>=0.1.2
Requires-Dist: brill-postagger<1.0.0,>=0.1.2
